MANIFEST.in
README.md
requirements.txt
setup.py
test-requirements.txt
ambariclient/__init__.py
ambariclient/base.py
ambariclient/client.py
ambariclient/events.py
ambariclient/exceptions.py
ambariclient/models.py
ambariclient/shell.py
ambariclient/utils.py
bin/ambari-shell
python_ambariclient.egg-info/PKG-INFO
python_ambariclient.egg-info/SOURCES.txt
python_ambariclient.egg-info/dependency_links.txt
python_ambariclient.egg-info/requires.txt
python_ambariclient.egg-info/top_level.txt