Metadata-Version: 1.1
Name: python-ambariclient
Version: 0.6.0
Summary: Client library for Apache Ambari.
Home-page: https://www.github.com/jimbobhickville/python-ambariclient
Author: Rackspace
Author-email: greg.hill@rackspace.com
License: UNKNOWN
Platform: UNKNOWN
Classifier: Development Status :: 3 - Alpha
Classifier: Intended Audience :: Developers
Classifier: Intended Audience :: Information Technology
Classifier: License :: OSI Approved :: Apache Software License
Classifier: Operating System :: OS Independent
Classifier: Programming Language :: Python
